README.rst
setup.py
dyn53/__init__.py
dyn53/conf.py
dyn53/dyn53.py
dyn53.egg-info/PKG-INFO
dyn53.egg-info/SOURCES.txt
dyn53.egg-info/dependency_links.txt
dyn53.egg-info/entry_points.txt
dyn53.egg-info/not-zip-safe
dyn53.egg-info/pbr.json
dyn53.egg-info/requires.txt
dyn53.egg-info/top_level.txt