Metadata-Version: 1.1
Name: dyn53
Version: 0.0.2
Summary: Update route 53 dns records based on current IP address.
Home-page: https://github.com/jfardello/dyn53
Author: José Fardello
Author-email: jmfardello@gmail.com
License: MIT
Platform: UNKNOWN
Classifier: Programming Language :: Python
Classifier: Programming Language :: Python :: 3
Classifier: Development Status :: 4 - Beta
Classifier: Environment :: Console
Classifier: Intended Audience :: Developers
Classifier: Intended Audience :: System Administrators
Classifier: Intended Audience :: Developers
Classifier: License :: OSI Approved :: MIT License
Classifier: Operating System :: OS Independent
